chguard/__init__.py
chguard/cli.py
chguard/db.py
chguard/restore.py
chguard/scan.py
chguard/util.py
chguard-0.3.3.dist-info/LICENCE
chguard-0.3.3.dist-info/METADATA
chguard-0.3.3.dist-info/WHEEL
chguard-0.3.3.dist-info/entry_points.txt
chguard-0.3.3.dist-info/RECORD
